.coveragerc
LICENSE
MANIFEST.in
README.adoc
requirements.txt
setup.py
tox.ini
docs/changelogs/0.1.0.adoc
docs/changelogs/0.2.0.adoc
docs/changelogs/0.2.1.adoc
docs/changelogs/next.adoc
reqs/requirements-coverage.txt
reqs/requirements-deploy.txt
reqs/requirements-flake8.txt
reqs/requirements-pylint.txt
reqs/requirements-tests.txt
src/awh/__init__.py
src/awh/_version.py
src/awh/app.py
src/awh/operate.py
src/awh/validator.py
src/awh.egg-info/PKG-INFO
src/awh.egg-info/SOURCES.txt
src/awh.egg-info/dependency_links.txt
src/awh.egg-info/entry_points.txt
src/awh.egg-info/requires.txt
src/awh.egg-info/top_level.txt
tests/apps/__init__.py
tests/apps/github.py
tests/apps/github.txt
tests/apps/gogs.py
tests/apps/gogs.txt