Metadata-Version: 1.1
Name: awh
Version: 0.2.1
Summary: Webhook creator and deployer
Home-page: https://gitlab.com/mgoral/awh
Author: Michał Góral
Author-email: dev@mgoral.org
License: MIT
Platform: linux
Classifier: Development Status :: 2 - Pre-Alpha
Classifier: Environment :: Console
Classifier: Intended Audience :: Developers
Classifier: License :: OSI Approved :: MIT License
Classifier: Natural Language :: English
Classifier: Operating System :: POSIX
Classifier: Programming Language :: Python :: 3 :: Only
Classifier: Topic :: Software Development :: Libraries
Classifier: Topic :: System :: Networking
Classifier: Topic :: System :: Networking :: Monitoring
Classifier: Topic :: System :: Systems Administration
